ae/gui_help/__init__.py
ae/gui_help/loc/de/Msg.txt
ae/gui_help/loc/en/Msg.txt
ae/gui_help/loc/es/Msg.txt
ae_gui_help-0.3.55.dist-info/LICENSE.md
ae_gui_help-0.3.55.dist-info/METADATA
ae_gui_help-0.3.55.dist-info/WHEEL
ae_gui_help-0.3.55.dist-info/top_level.txt
ae_gui_help-0.3.55.dist-info/RECORD
